odoo/addons/crm_lead_hide_add_property/README.rst
odoo/addons/crm_lead_hide_add_property/__init__.py
odoo/addons/crm_lead_hide_add_property/__manifest__.py
odoo/addons/crm_lead_hide_add_property/readme/CONTRIBUTORS.rst
odoo/addons/crm_lead_hide_add_property/readme/DESCRIPTION.rst
odoo/addons/crm_lead_hide_add_property/static/description/icon.png
odoo/addons/crm_lead_hide_add_property/static/description/index.html
odoo/addons/crm_lead_hide_add_property/views/crm_lead_views.xml
odoo_addon_crm_lead_hide_add_property-16.0.1.0.0.1.dist-info/METADATA
odoo_addon_crm_lead_hide_add_property-16.0.1.0.0.1.dist-info/WHEEL
odoo_addon_crm_lead_hide_add_property-16.0.1.0.0.1.dist-info/top_level.txt
odoo_addon_crm_lead_hide_add_property-16.0.1.0.0.1.dist-info/RECORD
